darkgray_dev_tools/__init__.py
darkgray_dev_tools/changelog.py
darkgray_dev_tools/darkgray_bump_version.py
darkgray_dev_tools/darkgray_collect_contributors.py
darkgray_dev_tools/darkgray_show_reviews.py
darkgray_dev_tools/darkgray_suggest_constraint.py
darkgray_dev_tools/darkgray_update_contributors.py
darkgray_dev_tools/exceptions.py
darkgray_dev_tools/milestones.py
darkgray_dev_tools/package_metadata.py
darkgray_dev_tools/version_replace.py
darkgray_dev_tools/versions.py
darkgray_dev_tools-0.3.0.dist-info/entry_points.txt
darkgray_dev_tools-0.3.0.dist-info/licenses/LICENSE
darkgray_dev_tools-0.3.0.dist-info/WHEEL
darkgray_dev_tools-0.3.0.dist-info/METADATA
darkgray_dev_tools-0.3.0.dist-info/RECORD
